azure/mgmt/cognitiveservices/__init__.py
azure/mgmt/cognitiveservices/_cognitive_services_management_client.py
azure/mgmt/cognitiveservices/_configuration.py
azure/mgmt/cognitiveservices/_patch.py
azure/mgmt/cognitiveservices/_serialization.py
azure/mgmt/cognitiveservices/_vendor.py
azure/mgmt/cognitiveservices/_version.py
azure/mgmt/cognitiveservices/py.typed
azure/mgmt/cognitiveservices/aio/__init__.py
azure/mgmt/cognitiveservices/aio/_cognitive_services_management_client.py
azure/mgmt/cognitiveservices/aio/_configuration.py
azure/mgmt/cognitiveservices/aio/_patch.py
azure/mgmt/cognitiveservices/aio/_vendor.py
azure/mgmt/cognitiveservices/aio/operations/__init__.py
azure/mgmt/cognitiveservices/aio/operations/_accounts_operations.py
azure/mgmt/cognitiveservices/aio/operations/_cognitive_services_management_client_operations.py
azure/mgmt/cognitiveservices/aio/operations/_commitment_plans_operations.py
azure/mgmt/cognitiveservices/aio/operations/_commitment_tiers_operations.py
azure/mgmt/cognitiveservices/aio/operations/_defender_for_ai_settings_operations.py
azure/mgmt/cognitiveservices/aio/operations/_deleted_accounts_operations.py
azure/mgmt/cognitiveservices/aio/operations/_deployments_operations.py
azure/mgmt/cognitiveservices/aio/operations/_encryption_scopes_operations.py
azure/mgmt/cognitiveservices/aio/operations/_location_based_model_capacities_operations.py
azure/mgmt/cognitiveservices/aio/operations/_model_capacities_operations.py
azure/mgmt/cognitiveservices/aio/operations/_models_operations.py
azure/mgmt/cognitiveservices/aio/operations/_network_security_perimeter_configurations_operations.py
azure/mgmt/cognitiveservices/aio/operations/_operations.py
azure/mgmt/cognitiveservices/aio/operations/_patch.py
azure/mgmt/cognitiveservices/aio/operations/_private_endpoint_connections_operations.py
azure/mgmt/cognitiveservices/aio/operations/_private_link_resources_operations.py
azure/mgmt/cognitiveservices/aio/operations/_rai_blocklist_items_operations.py
azure_mgmt_cognitiveservices-13.6.0.dist-info/LICENSE
azure_mgmt_cognitiveservices-13.6.0.dist-info/METADATA
azure_mgmt_cognitiveservices-13.6.0.dist-info/WHEEL
azure_mgmt_cognitiveservices-13.6.0.dist-info/top_level.txt
azure_mgmt_cognitiveservices-13.6.0.dist-info/RECORD
